[
  {
    "rootID": "20231014204443-00hymwd",
    "icon": "",
    "title": "航模飞行原理"
  },
  {
    "rootID": "20231015114514-69bw8ld",
    "icon": "",
    "title": "南瓜饼"
  },
  {
    "rootID": "20231015104833-j0d6ijs",
    "icon": "",
    "title": "糖醋汁"
  },
  {
    "rootID": "20230627141532-1gn03or",
    "icon": "",
    "title": "TypeScript"
  },
  {
    "rootID": "20230906145915-kalxewp",
    "icon": "",
    "title": "Vue3中Hooks"
  },
  {
    "rootID": "20230923135803-l24jyz0",
    "icon": "",
    "title": "TypeScript学习"
  },
  {
    "rootID": "20230927142224-4h05l44",
    "icon": "",
    "title": "WebSocket"
  },
  {
    "rootID": "20230705141547-jc20grx",
    "icon": "",
    "title": "设计模式"
  },
  {
    "rootID": "20230705141552-hsg1or3",
    "icon": "",
    "title": "工程化"
  },
  {
    "rootID": "20230705174327-s7t2a7w",
    "icon": "",
    "title": "移动端兼容性"
  },
  {
    "rootID": "20230705174417-igp8kb0",
    "icon": "",
    "title": "浏览器"
  },
  {
    "rootID": "20230705141527-58hd5dg",
    "icon": "",
    "title": "HTTP"
  },
  {
    "rootID": "20230705141442-w8xqlgz",
    "icon": "",
    "title": "JavaScript"
  },
  {
    "rootID": "20230705141433-88xtmqu",
    "icon": "",
    "title": "CSS3"
  },
  {
    "rootID": "20230705141410-oheofjl",
    "icon": "",
    "title": "HTML5"
  },
  {
    "rootID": "20230630085338-u9cl0ej",
    "icon": "",
    "title": "业务场景"
  },
  {
    "rootID": "20230825212043-wcxbr5s",
    "icon": "",
    "title": "Vue双向绑定原理"
  },
  {
    "rootID": "20230705141533-4bltiop",
    "icon": "",
    "title": "版本管理"
  },
  {
    "rootID": "20230705142423-dk7njah",
    "icon": "",
    "title": "新概念"
  },
  {
    "rootID": "20230706170718-7hwvf9s",
    "icon": "",
    "title": "支付"
  },
  {
    "rootID": "20230705142159-wv94ohn",
    "icon": "",
    "title": "uni-app"
  },
  {
    "rootID": "20230708170431-f9cj1wh",
    "icon": "",
    "title": "移动端兼容性"
  },
  {
    "rootID": "20230718125146-nrsff07",
    "icon": "",
    "title": "Git使用"
  },
  {
    "rootID": "20230728110417-7i2y8yl",
    "icon": "",
    "title": "前端项目框架搭建"
  },
  {
    "rootID": "20230718131959-1xfpylh",
    "icon": "",
    "title": "垃圾回收机制"
  },
  {
    "rootID": "20230729230318-nbvxp6l",
    "icon": "",
    "title": "前端安全"
  },
  {
    "rootID": "20230805160400-ije205z",
    "icon": "",
    "title": "Promise"
  },
  {
    "rootID": "20230807081452-huzm5v1",
    "icon": "",
    "title": "前端首页加载优化"
  },
  {
    "rootID": "20230807083057-4zngdwm",
    "icon": "",
    "title": "浏览器缓存"
  },
  {
    "rootID": "20230617142530-vpsp5fe",
    "icon": "",
    "title": "跨端注意"
  },
  {
    "rootID": "20230617140545-lboleuo",
    "icon": "",
    "title": "支付"
  },
  {
    "rootID": "20230617141731-ezh6h3p",
    "icon": "",
    "title": "登录"
  }
]